pyzpacker/__init__.py
pyzpacker/cmd.py
pyzpacker/pyzpacker.py
pyzpacker/version.py
pyzpacker-0.0.1.dist-info/LICENSE
pyzpacker-0.0.1.dist-info/METADATA
pyzpacker-0.0.1.dist-info/WHEEL
pyzpacker-0.0.1.dist-info/entry_points.txt
pyzpacker-0.0.1.dist-info/top_level.txt
pyzpacker-0.0.1.dist-info/RECORD
