Metadata-Version: 2.1
Name: pyzpacker
Version: 0.0.1
Summary: 将纯python项目模块打包为pyz包.
Author-email: hsz <hsz1273327@gmail.com>
License: MIT License
Project-URL: changelog, https://github.com/Python-Tools/pyzpacker/src/branch/main/CHANGELOG.md
Project-URL: documentation, https://github.com/Python-Tools/pyzpacker
Project-URL: homepage, https://github.com/Python-Tools/pyzpacker
Project-URL: repository, https://github.com/Python-Tools/pyzpacker
Keywords: tool
Platform: all
Classifier: License :: OSI Approved :: MIT License
Classifier: Programming Language :: Python :: 3
Classifier: Programming Language :: Python :: 3.10
Classifier: Programming Language :: Python :: 3.11
Classifier: Programming Language :: Python :: 3.12
Requires-Python: ~=3.10
License-File: LICENSE
Requires-Dist: chardet >=5.0.0
Provides-Extra: test
Requires-Dist: coverage ; extra == 'test'
Requires-Dist: mypy ; extra == 'test'
Requires-Dist: pycodestyle ; extra == 'test'
Requires-Dist: lxml ; extra == 'test'
